tmt/__init__.py
tmt/serial.py
tomaserial-1.0.3.dist-info/METADATA
tomaserial-1.0.3.dist-info/WHEEL
tomaserial-1.0.3.dist-info/licenses/LICENSE
tomaserial-1.0.3.dist-info/RECORD
