Metadata-Version: 2.1
Name: tomaserial
Version: 1.0.3
Summary: python serial and deserial
Project-URL: Homepage, https://github.com/sunlulu427/tomato
Project-URL: Bug Tracker, https://github.com/sunlulu427/tomato/issues
Author-email: "sunlulu.tomato" <sunlulu.tomato@bytedance.com>
License: Copyright (c) <2023> <copyright sunlulu.tomato@bytedance.com>
License-File: LICENSE
Classifier: License :: OSI Approved :: MIT License
Classifier: Operating System :: OS Independent
Classifier: Programming Language :: Python :: 3
Requires-Python: >=3.7
Requires-Dist: configparser; python_version >= '3.7'
